cv2/__init__.py
cv2/config-3.py
cv2/config.py
cv2/load_config_py2.py
cv2/load_config_py3.py
cv2/version.py
cv2/data/__init__.py
cv2/gapi/__init__.py
cv2/mat_wrapper/__init__.py
cv2/misc/__init__.py
cv2/misc/version.py
cv2/typing/__init__.py
cv2/utils/__init__.py
ddddocr/__init__.py
execjs/__init__.py
execjs/__main__.py
execjs/_abstract_runtime.py
execjs/_abstract_runtime_context.py
execjs/_exceptions.py
execjs/_external_runtime.py
execjs/_json2.py
execjs/_misc.py
execjs/_pyv8runtime.py
execjs/_runner_sources.py
execjs/_runtimes.py
execjs/runtime_names.py
fake_useragent/__init__.py
fake_useragent/errors.py
fake_useragent/fake.py
fake_useragent/log.py
fake_useragent/settings.py
fake_useragent/utils.py
loguru/__init__.py
loguru/_asyncio_loop.py
loguru/_better_exceptions.py
loguru/_colorama.py
loguru/_colorizer.py
loguru/_contextvars.py
loguru/_ctime_functions.py
loguru/_datetime.py
loguru/_defaults.py
loguru/_error_interceptor.py
loguru/_file_sink.py
loguru/_filters.py
loguru/_get_frame.py
loguru/_handler.py
loguru/_locks_machinery.py
loguru/_logger.py
loguru/_recattrs.py
loguru/_simple_sinks.py
loguru/_string_parsers.py
lxml/ElementInclude.py
lxml/__init__.py
lxml/_elementpath.py
lxml/builder.py
lxml/cssselect.py
lxml/doctestcompare.py
lxml/pyclasslookup.py
lxml/sax.py
lxml/usedoctest.py
lxml/html/ElementSoup.py
lxml/html/__init__.py
lxml/html/_diffcommand.py
lxml/html/_html5builder.py
lxml/html/_setmixin.py
lxml/html/builder.py
lxml/html/clean.py
lxml/html/defs.py
lxml/html/diff.py
lxml/html/formfill.py
lxml/html/html5parser.py
lxml/html/soupparser.py
lxml/html/usedoctest.py
lxml/includes/__init__.py
lxml/includes/extlibs/__init__.py
lxml/includes/libexslt/__init__.py
lxml/includes/libxml/__init__.py
lxml/includes/libxslt/__init__.py
lxml/isoschematron/__init__.py
requests/__init__.py
requests/__version__.py
requests/_internal_utils.py
requests/adapters.py
requests/api.py
requests/auth.py
requests/certs.py
requests/compat.py
requests/cookies.py
SpiderBox-0.0.1.dist-info/LICENSE.txt
SpiderBox-0.0.1.dist-info/METADATA
SpiderBox-0.0.1.dist-info/WHEEL
SpiderBox-0.0.1.dist-info/top_level.txt
SpiderBox-0.0.1.dist-info/RECORD
