Metadata-Version: 2.1
Name: SpiderBox
Version: 0.0.1
Summary: Package For Crawler
Home-page: https://github.com/JOUUUSKA/SpiderToolBox.git
Author: JOUSKA
Author-email: 1393827820@qq.com
License: UNKNOWN
Platform: UNKNOWN
Classifier: Programming Language :: Python :: 3
Classifier: License :: OSI Approved :: MIT License
Classifier: Operating System :: OS Independent
Requires-Python: >=3.6
License-File: LICENSE.txt
